{
  "results": [
    {
      "kp_id": 584084,
      "date": "2013-07-25",
      "json": "https://pleer.video/584084.json",
      "iframe": "https://pleer.video/584084"
    },
    {
      "kp_id": 569981,
      "date": "2013-07-25",
      "json": "https://pleer.video/569981.json",
      "iframe": "https://pleer.video/569981"
    },
    {
      "kp_id": 468937,
      "date": "2013-07-25",
      "json": "https://pleer.video/468937.json",
      "iframe": "https://pleer.video/468937"
    },
    {
      "kp_id": 492171,
      "date": "2013-07-25",
      "json": "https://pleer.video/492171.json",
      "iframe": "https://pleer.video/492171"
    },
    {
      "kp_id": 677566,
      "date": "2013-06-26",
      "json": "https://pleer.video/677566.json",
      "iframe": "https://pleer.video/677566"
    },
    {
      "kp_id": 596347,
      "date": "2013-06-26",
      "json": "https://pleer.video/596347.json",
      "iframe": "https://pleer.video/596347"
    },
    {
      "kp_id": 20954,
      "date": "2013-06-26",
      "json": "https://pleer.video/20954.json",
      "iframe": "https://pleer.video/20954"
    },
    {
      "kp_id": 707828,
      "date": "2013-06-26",
      "json": "https://pleer.video/707828.json",
      "iframe": "https://pleer.video/707828"
    },
    {
      "kp_id": 23737,
      "date": "2013-06-24",
      "json": "https://pleer.video/23737.json",
      "iframe": "https://pleer.video/23737"
    },
    {
      "kp_id": 595928,
      "date": "2013-06-04",
      "json": "https://pleer.video/595928.json",
      "iframe": "https://pleer.video/595928"
    },
    {
      "kp_id": 655729,
      "date": "2013-05-17",
      "json": "https://pleer.video/655729.json",
      "iframe": "https://pleer.video/655729"
    },
    {
      "kp_id": 565819,
      "date": "2013-05-17",
      "json": "https://pleer.video/565819.json",
      "iframe": "https://pleer.video/565819"
    },
    {
      "kp_id": 665100,
      "date": "2013-05-17",
      "json": "https://pleer.video/665100.json",
      "iframe": "https://pleer.video/665100"
    },
    {
      "kp_id": 745274,
      "date": "2013-05-17",
      "json": "https://pleer.video/745274.json",
      "iframe": "https://pleer.video/745274"
    },
    {
      "kp_id": 707261,
      "date": "2013-05-17",
      "json": "https://pleer.video/707261.json",
      "iframe": "https://pleer.video/707261"
    },
    {
      "kp_id": 568687,
      "date": "2013-05-17",
      "json": "https://pleer.video/568687.json",
      "iframe": "https://pleer.video/568687"
    },
    {
      "kp_id": 523135,
      "date": "2013-05-17",
      "json": "https://pleer.video/523135.json",
      "iframe": "https://pleer.video/523135"
    },
    {
      "kp_id": 592073,
      "date": "2013-05-17",
      "json": "https://pleer.video/592073.json",
      "iframe": "https://pleer.video/592073"
    },
    {
      "kp_id": 630398,
      "date": "2013-05-17",
      "json": "https://pleer.video/630398.json",
      "iframe": "https://pleer.video/630398"
    },
    {
      "kp_id": 462356,
      "date": "2013-05-17",
      "json": "https://pleer.video/462356.json",
      "iframe": "https://pleer.video/462356"
    },
    {
      "kp_id": 710276,
      "date": "2013-05-17",
      "json": "https://pleer.video/710276.json",
      "iframe": "https://pleer.video/710276"
    },
    {
      "kp_id": 504288,
      "date": "2013-05-17",
      "json": "https://pleer.video/504288.json",
      "iframe": "https://pleer.video/504288"
    },
    {
      "kp_id": 757978,
      "date": "2013-05-17",
      "json": "https://pleer.video/757978.json",
      "iframe": "https://pleer.video/757978"
    },
    {
      "kp_id": 673910,
      "date": "2013-05-17",
      "json": "https://pleer.video/673910.json",
      "iframe": "https://pleer.video/673910"
    },
    {
      "kp_id": 712576,
      "date": "2013-05-17",
      "json": "https://pleer.video/712576.json",
      "iframe": "https://pleer.video/712576"
    },
    {
      "kp_id": 518094,
      "date": "2013-05-17",
      "json": "https://pleer.video/518094.json",
      "iframe": "https://pleer.video/518094"
    },
    {
      "kp_id": 669841,
      "date": "2013-05-17",
      "json": "https://pleer.video/669841.json",
      "iframe": "https://pleer.video/669841"
    },
    {
      "kp_id": 591399,
      "date": "2013-05-17",
      "json": "https://pleer.video/591399.json",
      "iframe": "https://pleer.video/591399"
    },
    {
      "kp_id": 695959,
      "date": "2013-05-17",
      "json": "https://pleer.video/695959.json",
      "iframe": "https://pleer.video/695959"
    },
    {
      "kp_id": 613969,
      "date": "2013-05-17",
      "json": "https://pleer.video/613969.json",
      "iframe": "https://pleer.video/613969"
    },
    {
      "kp_id": 663698,
      "date": "2013-05-17",
      "json": "https://pleer.video/663698.json",
      "iframe": "https://pleer.video/663698"
    },
    {
      "kp_id": 635224,
      "date": "2013-05-17",
      "json": "https://pleer.video/635224.json",
      "iframe": "https://pleer.video/635224"
    },
    {
      "kp_id": 659655,
      "date": "2013-05-17",
      "json": "https://pleer.video/659655.json",
      "iframe": "https://pleer.video/659655"
    },
    {
      "kp_id": 623972,
      "date": "2013-05-17",
      "json": "https://pleer.video/623972.json",
      "iframe": "https://pleer.video/623972"
    },
    {
      "kp_id": 648441,
      "date": "2013-05-17",
      "json": "https://pleer.video/648441.json",
      "iframe": "https://pleer.video/648441"
    },
    {
      "kp_id": 687152,
      "date": "2013-05-17",
      "json": "https://pleer.video/687152.json",
      "iframe": "https://pleer.video/687152"
    },
    {
      "kp_id": 602707,
      "date": "2013-05-17",
      "json": "https://pleer.video/602707.json",
      "iframe": "https://pleer.video/602707"
    },
    {
      "kp_id": 557837,
      "date": "2013-05-17",
      "json": "https://pleer.video/557837.json",
      "iframe": "https://pleer.video/557837"
    },
    {
      "kp_id": 733784,
      "date": "2013-05-07",
      "json": "https://pleer.video/733784.json",
      "iframe": "https://pleer.video/733784"
    },
    {
      "kp_id": 714119,
      "date": "2013-05-07",
      "json": "https://pleer.video/714119.json",
      "iframe": "https://pleer.video/714119"
    },
    {
      "kp_id": 589545,
      "date": "2013-05-07",
      "json": "https://pleer.video/589545.json",
      "iframe": "https://pleer.video/589545"
    },
    {
      "kp_id": 712716,
      "date": "2013-05-07",
      "json": "https://pleer.video/712716.json",
      "iframe": "https://pleer.video/712716"
    },
    {
      "kp_id": 693962,
      "date": "2013-05-07",
      "json": "https://pleer.video/693962.json",
      "iframe": "https://pleer.video/693962"
    },
    {
      "kp_id": 623645,
      "date": "2013-05-07",
      "json": "https://pleer.video/623645.json",
      "iframe": "https://pleer.video/623645"
    },
    {
      "kp_id": 609627,
      "date": "2013-05-07",
      "json": "https://pleer.video/609627.json",
      "iframe": "https://pleer.video/609627"
    },
    {
      "kp_id": 496899,
      "date": "2013-05-07",
      "json": "https://pleer.video/496899.json",
      "iframe": "https://pleer.video/496899"
    },
    {
      "kp_id": 714718,
      "date": "2013-04-26",
      "json": "https://pleer.video/714718.json",
      "iframe": "https://pleer.video/714718"
    },
    {
      "kp_id": 596221,
      "date": "2013-04-26",
      "json": "https://pleer.video/596221.json",
      "iframe": "https://pleer.video/596221"
    },
    {
      "kp_id": 522902,
      "date": "2013-03-28",
      "json": "https://pleer.video/522902.json",
      "iframe": "https://pleer.video/522902"
    },
    {
      "kp_id": 77441,
      "date": "2013-03-21",
      "json": "https://pleer.video/77441.json",
      "iframe": "https://pleer.video/77441"
    },
    {
      "kp_id": 669525,
      "date": "2013-03-06",
      "json": "https://pleer.video/669525.json",
      "iframe": "https://pleer.video/669525"
    },
    {
      "kp_id": 722983,
      "date": "2013-03-06",
      "json": "https://pleer.video/722983.json",
      "iframe": "https://pleer.video/722983"
    },
    {
      "kp_id": 484767,
      "date": "2013-03-06",
      "json": "https://pleer.video/484767.json",
      "iframe": "https://pleer.video/484767"
    },
    {
      "kp_id": 682087,
      "date": "2013-03-06",
      "json": "https://pleer.video/682087.json",
      "iframe": "https://pleer.video/682087"
    },
    {
      "kp_id": 678652,
      "date": "2013-03-06",
      "json": "https://pleer.video/678652.json",
      "iframe": "https://pleer.video/678652"
    },
    {
      "kp_id": 41830,
      "date": "2013-02-26",
      "json": "https://pleer.video/41830.json",
      "iframe": "https://pleer.video/41830"
    },
    {
      "kp_id": 391762,
      "date": "2013-02-26",
      "json": "https://pleer.video/391762.json",
      "iframe": "https://pleer.video/391762"
    },
    {
      "kp_id": 464484,
      "date": "2013-02-26",
      "json": "https://pleer.video/464484.json",
      "iframe": "https://pleer.video/464484"
    },
    {
      "kp_id": 160977,
      "date": "2013-02-26",
      "json": "https://pleer.video/160977.json",
      "iframe": "https://pleer.video/160977"
    },
    {
      "kp_id": 8335,
      "date": "2013-02-26",
      "json": "https://pleer.video/8335.json",
      "iframe": "https://pleer.video/8335"
    },
    {
      "kp_id": 580545,
      "date": "2013-02-19",
      "json": "https://pleer.video/580545.json",
      "iframe": "https://pleer.video/580545"
    },
    {
      "kp_id": 573206,
      "date": "2013-02-19",
      "json": "https://pleer.video/573206.json",
      "iframe": "https://pleer.video/573206"
    },
    {
      "kp_id": 477647,
      "date": "2013-02-05",
      "json": "https://pleer.video/477647.json",
      "iframe": "https://pleer.video/477647"
    },
    {
      "kp_id": 647451,
      "date": "2013-01-29",
      "json": "https://pleer.video/647451.json",
      "iframe": "https://pleer.video/647451"
    },
    {
      "kp_id": 661609,
      "date": "2013-01-29",
      "json": "https://pleer.video/661609.json",
      "iframe": "https://pleer.video/661609"
    },
    {
      "kp_id": 634300,
      "date": "2013-01-22",
      "json": "https://pleer.video/634300.json",
      "iframe": "https://pleer.video/634300"
    },
    {
      "kp_id": 596378,
      "date": "2013-01-22",
      "json": "https://pleer.video/596378.json",
      "iframe": "https://pleer.video/596378"
    },
    {
      "kp_id": 506432,
      "date": "2013-01-22",
      "json": "https://pleer.video/506432.json",
      "iframe": "https://pleer.video/506432"
    },
    {
      "kp_id": 572772,
      "date": "2013-01-22",
      "json": "https://pleer.video/572772.json",
      "iframe": "https://pleer.video/572772"
    },
    {
      "kp_id": 586873,
      "date": "2013-01-22",
      "json": "https://pleer.video/586873.json",
      "iframe": "https://pleer.video/586873"
    },
    {
      "kp_id": 694014,
      "date": "2013-01-22",
      "json": "https://pleer.video/694014.json",
      "iframe": "https://pleer.video/694014"
    },
    {
      "kp_id": 665366,
      "date": "2013-01-22",
      "json": "https://pleer.video/665366.json",
      "iframe": "https://pleer.video/665366"
    },
    {
      "kp_id": 663814,
      "date": "2013-01-22",
      "json": "https://pleer.video/663814.json",
      "iframe": "https://pleer.video/663814"
    },
    {
      "kp_id": 652520,
      "date": "2013-01-22",
      "json": "https://pleer.video/652520.json",
      "iframe": "https://pleer.video/652520"
    },
    {
      "kp_id": 647671,
      "date": "2013-01-21",
      "json": "https://pleer.video/647671.json",
      "iframe": "https://pleer.video/647671"
    },
    {
      "kp_id": 521689,
      "date": "2013-01-21",
      "json": "https://pleer.video/521689.json",
      "iframe": "https://pleer.video/521689"
    },
    {
      "kp_id": 433311,
      "date": "2013-01-21",
      "json": "https://pleer.video/433311.json",
      "iframe": "https://pleer.video/433311"
    },
    {
      "kp_id": 577648,
      "date": "2013-01-21",
      "json": "https://pleer.video/577648.json",
      "iframe": "https://pleer.video/577648"
    },
    {
      "kp_id": 597580,
      "date": "2013-01-21",
      "json": "https://pleer.video/597580.json",
      "iframe": "https://pleer.video/597580"
    },
    {
      "kp_id": 715464,
      "date": "2013-01-21",
      "json": "https://pleer.video/715464.json",
      "iframe": "https://pleer.video/715464"
    },
    {
      "kp_id": 506456,
      "date": "2013-01-21",
      "json": "https://pleer.video/506456.json",
      "iframe": "https://pleer.video/506456"
    },
    {
      "kp_id": 446090,
      "date": "2012-12-28",
      "json": "https://pleer.video/446090.json",
      "iframe": "https://pleer.video/446090"
    },
    {
      "kp_id": 431134,
      "date": "2012-12-28",
      "json": "https://pleer.video/431134.json",
      "iframe": "https://pleer.video/431134"
    },
    {
      "kp_id": 732210,
      "date": "2012-12-26",
      "json": "https://pleer.video/732210.json",
      "iframe": "https://pleer.video/732210"
    },
    {
      "kp_id": 580190,
      "date": "2012-12-05",
      "json": "https://pleer.video/580190.json",
      "iframe": "https://pleer.video/580190"
    },
    {
      "kp_id": 587867,
      "date": "2012-11-29",
      "json": "https://pleer.video/587867.json",
      "iframe": "https://pleer.video/587867"
    },
    {
      "kp_id": 477742,
      "date": "2012-11-29",
      "json": "https://pleer.video/477742.json",
      "iframe": "https://pleer.video/477742"
    },
    {
      "kp_id": 262587,
      "date": "2012-11-29",
      "json": "https://pleer.video/262587.json",
      "iframe": "https://pleer.video/262587"
    },
    {
      "kp_id": 195429,
      "date": "2012-11-29",
      "json": "https://pleer.video/195429.json",
      "iframe": "https://pleer.video/195429"
    },
    {
      "kp_id": 462294,
      "date": "2012-11-29",
      "json": "https://pleer.video/462294.json",
      "iframe": "https://pleer.video/462294"
    },
    {
      "kp_id": 481086,
      "date": "2012-11-22",
      "json": "https://pleer.video/481086.json",
      "iframe": "https://pleer.video/481086"
    },
    {
      "kp_id": 468192,
      "date": "2012-11-13",
      "json": "https://pleer.video/468192.json",
      "iframe": "https://pleer.video/468192"
    },
    {
      "kp_id": 587288,
      "date": "2012-11-06",
      "json": "https://pleer.video/587288.json",
      "iframe": "https://pleer.video/587288"
    },
    {
      "kp_id": 462336,
      "date": "2012-11-06",
      "json": "https://pleer.video/462336.json",
      "iframe": "https://pleer.video/462336"
    },
    {
      "kp_id": 586584,
      "date": "2012-11-06",
      "json": "https://pleer.video/586584.json",
      "iframe": "https://pleer.video/586584"
    },
    {
      "kp_id": 582764,
      "date": "2012-11-06",
      "json": "https://pleer.video/582764.json",
      "iframe": "https://pleer.video/582764"
    },
    {
      "kp_id": 577673,
      "date": "2012-11-06",
      "json": "https://pleer.video/577673.json",
      "iframe": "https://pleer.video/577673"
    },
    {
      "kp_id": 506239,
      "date": "2012-11-06",
      "json": "https://pleer.video/506239.json",
      "iframe": "https://pleer.video/506239"
    },
    {
      "kp_id": 280967,
      "date": "2012-11-06",
      "json": "https://pleer.video/280967.json",
      "iframe": "https://pleer.video/280967"
    },
    {
      "kp_id": 590430,
      "date": "2012-10-11",
      "json": "https://pleer.video/590430.json",
      "iframe": "https://pleer.video/590430"
    }
  ],
  "pages": {
    "current": 21,
    "last": 25,
    "url": {
      "prev": "https://pleer.video/movies20.json",
      "next": "https://pleer.video/movies22.json"
    }
  }
}